{"chunk_definitions":[{"row":36,"row_count":1,"visible":true,"expansion_state":0,"options":{"engine":"r","label":"setup","include":false,"dev":"png"},"document_id":"F8E24063","chunk_id":"csetup_chunk","chunk_label":"setup"},{"row":46,"row_count":1,"visible":true,"expansion_state":0,"options":{},"document_id":"F8E24063","chunk_id":"c3khotubpy2f6","chunk_label":"unnamed-chunk-1"},{"row":51,"row_count":1,"visible":true,"expansion_state":0,"options":{},"document_id":"F8E24063","chunk_id":"cz2pziyzy6f8v","chunk_label":"unnamed-chunk-2"},{"row":64,"row_count":1,"visible":true,"expansion_state":0,"options":{},"document_id":"F8E24063","chunk_id":"cl0raj265blwt","chunk_label":"unnamed-chunk-3"},{"row":76,"row_count":1,"visible":true,"expansion_state":0,"options":{},"document_id":"F8E24063","chunk_id":"cg7htmau4e9sw","chunk_label":"unnamed-chunk-4"},{"row":87,"row_count":1,"visible":true,"expansion_state":0,"options":{},"document_id":"F8E24063","chunk_id":"cdrnufv039mps","chunk_label":"unnamed-chunk-5"},{"row":118,"row_count":1,"visible":true,"expansion_state":0,"options":{},"document_id":"F8E24063","chunk_id":"cs94f4y0st2yb","chunk_label":"unnamed-chunk-6"},{"row":147,"row_count":1,"visible":true,"expansion_state":0,"options":{},"document_id":"F8E24063","chunk_id":"cd3qfcfrwcv9m","chunk_label":"unnamed-chunk-7"},{"row":164,"row_count":1,"visible":true,"expansion_state":0,"options":{"engine":"r","results":"asis","label":"unnamed-chunk-1","dev":"png"},"document_id":"F8E24063","chunk_id":"c50abgmiynbpu","chunk_label":"unnamed-chunk-8"}],"doc_write_time":1747685445,"working_dir":null,"default_chunk_options":{"echo":false,"message":false,"warning":false,"comment":""},"chunk_rendered_width":700}